examples/__init__.py
examples/buy_and_hold_strategy.py
examples/download_historical_data_from_ib.py
examples/download_ib_contract_info.py
examples/live_engine.py
examples/prepare_trading_session.py
examples/strategy/__init__.py
examples/strategy/active_buy_sell_strength_strategy.py
examples/strategy/double_moving_average_cross_strategy.py
examples/strategy/dual_thrust_strategy.py
examples/strategy/dual_time_frame_strategy.py
examples/strategy/kdj_mnqemacross_strategy.py
examples/strategy/kdj_strategy.py
examples/strategy/kdj_strategy_v2.py
examples/strategy/moving_average_cross_strategy.py
examples/strategy/order_per_interval_strategy.py
quanttrader/__init__.py
quanttrader/backtest_engine.py
quanttrader/backtest_gym_engine.py
quanttrader/portfolio_env.py
quanttrader/trading_env.py
quanttrader/version.py
quanttrader/account/__init__.py
quanttrader/account/account_event.py
quanttrader/account/account_manager.py
quanttrader/brokerage/__init__.py
quanttrader/brokerage/backtest_brokerage.py
quanttrader/brokerage/brokerage_base.py
quanttrader/brokerage/ib_brokerage.py
quanttrader/data/__init__.py
quanttrader/data/backtest_data_feed.py
quanttrader/data/bar_event.py
quanttrader/data/data_board.py
quanttrader/data/data_feed_base.py
quanttrader/data/live_data_feed.py
quanttrader/data/tick_event.py
quanttrader/event/__init__.py
quanttrader/event/backtest_event_engine.py
quanttrader/event/event.py
quanttrader/event/live_event_engine.py
quanttrader/gui/__init__.py
quanttrader/gui/ui_account_window.py
quanttrader/gui/ui_fill_window.py
quanttrader/gui/ui_log_window.py
quanttrader/gui/ui_main_window.py
quanttrader/gui/ui_order_window.py
quanttrader/gui/ui_position_menu.py
quanttrader/gui/ui_position_window.py
quanttrader/gui/ui_risk_menu.py
quanttrader/gui/ui_strategy_window.py
quanttrader/gui/ui_trade_menu.py
quanttrader/log/__init__.py
quanttrader/log/tick_recorder.py
quanttrader/log/trade_recorder.py
quanttrader/log/trade_recorder_base.py
quanttrader/order/__init__.py
quanttrader-0.5.5.dist-info/LICENSE
quanttrader-0.5.5.dist-info/METADATA
quanttrader-0.5.5.dist-info/WHEEL
quanttrader-0.5.5.dist-info/top_level.txt
quanttrader-0.5.5.dist-info/RECORD
