Metadata-Version: 2.1
Name: quanttrader
Version: 0.5.5
Summary: quanttrader backtest and live trading library
Home-page: https://github.com/letianzj/quanttrader
Author: Letian Wang
Author-email: letian.zj@gmail.com
License: Apache 2.0
Keywords: quanttrader strategy backtest live trading
Platform: UNKNOWN
Classifier: Development Status :: 4 - Beta
Classifier: Intended Audience :: Developers
Classifier: Programming Language :: Python :: 3.7
Requires-Python: >=3.7.*
Requires-Dist: matplotlib (>=3.0.3)
Requires-Dist: numpy (>=1.18.0)
Requires-Dist: pandas (>=1.0.5)
Requires-Dist: psutil (>=5.7.0)
Requires-Dist: pytz (>=2018.9)
Requires-Dist: scipy (>=1.4.1)
Requires-Dist: scikit-learn (>=0.22.1)
Requires-Dist: seaborn (>=0.10.1)
Requires-Dist: pytest (>=3.6.4)
Requires-Dist: PyQt5 (>=5.10.1)
Requires-Dist: QDarkStyle (>=2.8)
Requires-Dist: PyYAML (>=5.3.1)
Requires-Dist: ibapi (>=9.76.1)
Requires-Dist: gym (>=0.21.0)
